LICENSE
MANIFEST.in
README.md
setup.py
cmsplugin_hoverimage/__init__.py
cmsplugin_hoverimage/cms_plugins.py
cmsplugin_hoverimage/models.py
cmsplugin_hoverimage/tests.py
cmsplugin_hoverimage/views.py
cmsplugin_hoverimage.egg-info/PKG-INFO
cmsplugin_hoverimage.egg-info/SOURCES.txt
cmsplugin_hoverimage.egg-info/dependency_links.txt
cmsplugin_hoverimage.egg-info/requires.txt
cmsplugin_hoverimage.egg-info/top_level.txt
cmsplugin_hoverimage/migrations/.0001_initial.py.swp
cmsplugin_hoverimage/migrations/0001_initial.py
cmsplugin_hoverimage/migrations/0001_initial.pyc
cmsplugin_hoverimage/migrations/__init__.py
cmsplugin_hoverimage/templates/hoverimage/.video.html.swp
cmsplugin_hoverimage/templates/hoverimage/image.html