Metadata-Version: 1.0
Name: cmsplugin-hoverimage
Version: 0.0.1
Summary: Plugin for Django CMS that displays a image that changes on hover.
Home-page: http://github.com/codemill/cmsplugin-hoverimage
Author: Ludvig Widman, CodeMill AB
Author-email: opensource@codemill.se
License: UNKNOWN
Platform: UNKNOWN
